sphinx_computron/__init__.py
sphinx_computron-1.0.0.dist-info/AUTHORS
sphinx_computron-1.0.0.dist-info/LICENSE.txt
sphinx_computron-1.0.0.dist-info/METADATA
sphinx_computron-1.0.0.dist-info/WHEEL
sphinx_computron-1.0.0.dist-info/top_level.txt
sphinx_computron-1.0.0.dist-info/RECORD
