Metadata-Version: 2.1
Name: sphinx-computron
Version: 1.0.0
Summary: Sphinx support for execution of python code from code blocks or files. Original code by JP Senior.
Home-page: https://github.com/pavel-kirienko/sphinx-computron
Author: JP Senior, Pavel Kirienko
Author-email: pavel.kirienko@gmail.com
License: MIT
Keywords: sphinx extension directive
Platform: UNKNOWN
Classifier: Intended Audience :: Developers
Classifier: Framework :: Sphinx :: Extension
Classifier: License :: OSI Approved :: MIT License
Classifier: Programming Language :: Python :: 3.7
Classifier: Programming Language :: Python :: 3.8
License-File: LICENSE.txt
License-File: AUTHORS
Requires-Dist: docutils
Requires-Dist: sphinx
